MANIFEST.in
setup.py
techela/__init__.py
techela/app.py
techela/open.py
techela.egg-info/PKG-INFO
techela.egg-info/SOURCES.txt
techela.egg-info/dependency_links.txt
techela.egg-info/requires.txt
techela.egg-info/top_level.txt
techela/bin/techela
techela/bin/techela-el
techela/elisp/techela.el
techela/static/.DS_Store
techela/static/jquery-latest.js
techela/static/jquery.metadata.js
techela/static/jquery.tablesorter.js
techela/static/jquery.tablesorter.min.js
techela/static/techela.js
techela/static/themes/.DS_Store
techela/static/themes/blue/asc.gif
techela/static/themes/blue/bg.gif
techela/static/themes/blue/blue.zip
techela/static/themes/blue/desc.gif
techela/static/themes/blue/style.css
techela/static/themes/green/asc.png
techela/static/themes/green/bg.png
techela/static/themes/green/desc.png
techela/static/themes/green/green.zip
techela/static/themes/green/style.css
techela/templates/about.html
techela/templates/admin.html
techela/templates/course-info.html
techela/templates/email.html
techela/templates/grade-assignment.html
techela/templates/gradebook.html
techela/templates/gradebook_one.html
techela/templates/hello.html
techela/templates/password_error.html
techela/templates/roster.html
techela/templates/setup.html