Metadata-Version: 1.0
Name: techela
Version: 3.2.4
Summary: Utilities for techela.
Home-page: http://github.com/jkitchin/techela
Author: John Kitchin
Author-email: jkitchin@andrew.cmu.edu
License: GPL
Platform: UNKNOWN
